roman/__init__.py
roman/roman.py
roman/templatetags/__init__.py
roman/templatetags/roman_tags.py
roman/tests/__init__.py
roman/tests/settings.py
roman/tests/test_roman.py
roman/utils/__init__.py
roman/utils/roman.py
django_roman-0.2.3.dist-info/LICENSE
django_roman-0.2.3.dist-info/METADATA
django_roman-0.2.3.dist-info/WHEEL
django_roman-0.2.3.dist-info/top_level.txt
django_roman-0.2.3.dist-info/RECORD
